{
    "en": {
        "title": "About Me",
        "info": {
            "title": "Personal Information",
            "name": {
                "title": "Name",
                "text": "Kevin Svitač"
            },
            "email": {
                "title": "E-mail"
            },
            "location": {
                "title": "Location",
                "text": "Slovakia"
            }
        },
        "social": {
            "title": "Social Media"
        },
        "skills": {
            "title": "Skills"
        },
        "print": "Print"
    },
    "sk": {
        "title": "O mne",
        "info": {
            "title": "Osobné Údaje",
            "name": {
                "title": "Meno",
                "text": "Kevin Svitač"
            },
            "email": {
                "title": "E-mail",
                "text": "kevin@svit.ac"
            },
            "location": {
                "title": "Krajina",
                "text": "Slovensko"
            }
        },
        "social": {
            "title": "Sociálne Siete"
        },
        "skills": {
            "title": "Zručnosti"
        },
        "print": "Vytlačiť"
    }
}
